gpi-0.1.1.dist-info/metadata.json
gpi-0.1.1.dist-info/DESCRIPTION.rst
gpi-0.1.1.dist-info/top_level.txt
gpi-0.1.1.dist-info/METADATA
gpi-0.1.1.dist-info/WHEEL
gpi-0.1.1.dist-info/RECORD
gpi/__init__.py
gpi/installer.py
gpi/web.py
gpi-0.1.1.data/scripts/gpi
