Metadata-Version: 2.0
Name: gpi
Version: 0.1.1
Summary: The GIMP Plugin Installer command-line tool
Home-page: https://gpi.tschuy.com
Author: Evan Tschuy
Author-email: evantschuy@gmail.com
License: UNKNOWN
Platform: UNKNOWN
